Workbook

Sheet WBS
A1: WBS Code | B1: WS # | C1: Workstream | D1: Task / Work Package | E1: Description | F1: Phase | G1: Component | H1: Source Doc(s) | I1: Effort (PD) | J1: Dependencies | K1: Key Deliverable | L1: Primary Role | M1: Tickets | N1: Done | O1: Partial | P1: Not Started | Q1: % Done | R1: Status (audit 2026-06-10) | S1: Completion Phase (v3)
A2: 1.1 | B2: 1 | C2: 1. Project Management & Mobilization | D2: Project kickoff & mobilization | E2: Team onboarding, access, comms plan, tooling setup. | F2: 1 | G2: Cross-cutting | H2: DOC-00, PM-14 | I2: 5 | J2: - | K2: Kickoff pack, RACI confirmed | L2: PM | M2: 15 | N2: 0 | O2: 1 | P2: 14 | Q2: 0% | R2: IN PROGRESS | S2: R0
A3: 1.2 | B3: 1 | C3: 1. Project Management & Mobilization | D3: Requirements walkthrough & open-item resolution | E3: Confirm scope; drive OI-01 (customer approval UX), OI-02 (tax-invoice API), OI-03 (BOK format) to decisions. | F3: 1 | G3: Cross-cutting | H3: All | I3: 6 | J3: 1.1 | K3: Clarification log, updated assumptions | L3: BA | M3: 20 | N3: 0 | O3: 0 | P3: 20 | Q3: 0% | R3: NOT STARTED | S3: R0
A4: 1.3 | B4: 1 | C4: 1. Project Management & Mobilization | D4: Delivery plan, environments & estimates | E4: Detailed schedule, environment plan, refined estimates per this WBS. | F4: 1 | G4: Cross-cutting | H4: PM-14 | I4: 5 | J4: 1.1 | K4: Baselined plan | L4: PM | M4: 33 | N4: 3 | O4: 3 | P4: 27 | Q4: 9% | R4: IN PROGRESS | S4: R0
A5: 1.4 | B5: 1 | C5: 1. Project Management & Mobilization | D5: Architecture & design sign-off | E5: Review SAD/data model with GME; approve approach. | F5: 1 | G5: Cross-cutting | H5: SAD-02 | I5: 4 | J5: 2.1,3.1 | K5: Signed-off design | L5: ARCH | M5: 30 | N5: 0 | O5: 0 | P5: 30 | Q5: 0% | R5: NOT STARTED | S5: R0
A6: 1.5 | B6: 1 | C6: 1. Project Management & Mobilization | D6: Ongoing project management & reporting | E6: Sprint ceremonies, status reporting, risk/RAID upkeep across all phases. | F6: 1 | G6: Cross-cutting | H6: PM-14 | I6: 40 | J6: 1.3 | K6: Status reports, RAID log | L6: PM | M6: 30 | N6: 0 | O6: 0 | P6: 30 | Q6: 0% | R6: NOT STARTED | S6: R8
A7: 1.6 | B7: 1 | C7: 1. Project Management & Mobilization | D7: As-built documentation & handover | E7: Update specs to as-built, API docs, ops handover materials. | F7: 4 | G7: Cross-cutting | H7: DOC-00 | I7: 10 | J7: 16.5 | K7: As-built docs | L7: BA | M7: 22 | N7: 0 | O7: 0 | P7: 22 | Q7: 0% | R7: NOT STARTED | S7: R8
A8: 2.1 | B8: 2 | C8: 2. Architecture & Technical Foundation | D8: Finalize system architecture & tech stack | E8: Component architecture, service boundaries, tech choices. | F8: 1 | G8: Cross-cutting | H8: SAD-02 | I8: 6 | J8: 1.1 | K8: Architecture baseline | L8: ARCH | M8: 33 | N8: 1 | O8: 16 | P8: 16 | Q8: 3% | R8: IN PROGRESS | S8: R0
A9: 2.2 | B9: 2 | C9: 2. Architecture & Technical Foundation | D9: Service/module structure & scaffolding | E9: Hub Core, scheme adapters, API gateway module skeletons. | F9: 1 | G9: Hub Core | H9: SAD-02 | I9: 5 | J9: 2.1 | K9: Service skeletons | L9: ARCH | M9: 28 | N9: 2 | O9: 20 | P9: 6 | Q9: 7% | R9: IN PROGRESS | S9: R0
A10: 2.3 | B10: 2 | C10: 2. Architecture & Technical Foundation | D10: Coding standards, repo, branching, CI scaffold | E10: Repos, branching model, lint/format, build scaffold. | F10: 1 | G10: Cross-cutting | H10: OPS-13 | I10: 4 | J10: 2.1 | K10: Standards & repo | L10: ARCH | M10: 27 | N10: 0 | O10: 0 | P10: 27 | Q10: 0% | R10: NOT STARTED | S10: R0
A11: 2.4 | B11: 2 | C11: 2. Architecture & Technical Foundation | D11: Cross-cutting libs: money, currency, errors | E11: Decimal/money type, currency scale, canonical error model. | F11: 1 | G11: Hub Core | H11: RATE-04, API-05 | I11: 6 | J11: 2.3 | K11: Shared libraries | L11: BE | M11: 25 | N11: 0 | O11: 14 | P11: 11 | Q11: 0% | R11: IN PROGRESS | S11: R1
A12: 2.5 | B12: 2 | C12: 2. Architecture & Technical Foundation | D12: Configuration framework (config-not-code) | E12: Schemes/partners/rules/rates as runtime config; no deploy to add. | F12: 1 | G12: Cross-cutting | H12: NFR-10, SAD-02 | I12: 8 | J12: 2.4 | K12: Config framework | L12: BE | M12: 33 | N12: 0 | O12: 4 | P12: 29 | Q12: 0% | R12: IN PROGRESS | S12: R1
A13: 2.6 | B13: 2 | C13: 2. Architecture & Technical Foundation | D13: Internationalization framework | E13: Multi-currency (KRW/USD/…), Korean/English support. | F13: 1 | G13: Cross-cutting | H13: NFR-10 | I13: 4 | J13: 2.4 | K13: i18n framework | L13: BE | M13: 26 | N13: 0 | O13: 0 | P13: 26 | Q13: 0% | R13: NOT STARTED | S13: R4
... A125: 16.6 | B125: 16 | C125: 16. Deployment, Go-Live & Hypercare | D125: Operational runbook handover & training | E125: Runbook walkthrough, Ops training. | F125: 4 | G125: Cross-cutting | H125: OPS-13 | I125: 5 | J125: 16.5 | K125: Runbook + training | L125: DevOps | M125: 27 | N125: 0 | O125: 0 | P125: 27 | Q125: 0% | R125: NOT STARTED | S125: R8
A126: 17.1 | B126: 17 | C126: 17. Real-Stack Gap Closure | D126: Docker-capable build & CI environment | E126: Stand up a build host/runner with Docker so docker-compose + Testcontainers can run; wire into GitHub Actions. Single biggest unlock: every H2/stub PARTIAL depends on it. | F126: 1 | G126: platform-infra | H126: Audit 2026-06-10 / WBS v3 re-baseline | I126: 5 | J126: - | K126: CI job runs docker-compose stack + Testcontainers ITs green | L126: DevOps | M126: 3 | R126: NOT STARTED | S126: R0
A127: 17.2 | B127: 17 | C127: 17. Real-Stack Gap Closure | D127: H2 → real PostgreSQL per service | E127: Replace H2-in-PG-mode test DBs with real PostgreSQL via docker-compose + Testcontainers ITs for all 12 persistence-bearing services; verify Flyway migrations against PG 16. | F127: 1 | G127: all data services | H127: Audit 2026-06-10 / WBS v3 re-baseline | I127: 18 | J127: 17.1 | K127: Repository ITs green on real PostgreSQL for 12 services | L127: Backend | M127: 12 | R127: NOT STARTED | S127: R1
A128: 17.3 | B128: 17 | C128: 17. Real-Stack Gap Closure | D128: Redis wiring (cache/TTL/idempotency) | E128: Replace in-memory stores with Redis: rate-quote TTL store (rate-fx), idempotency keys (transaction-mgmt/api-gateway), config cache (config-registry). | F128: 1 | G128: rate-fx, txn-mgmt, config-registry | H128: Audit 2026-06-10 / WBS v3 re-baseline | I128: 6 | J128: 17.1 | K128: Redis-backed stores with ITs | L128: Backend | M128: 3 | R128: NOT STARTED | S128: R1
A129: 17.4 | B129: 17 | C129: 17. Real-Stack Gap Closure | D129: Kafka producer + Schema Registry | E129: Implement KafkaEventPublisher behind lib-events EventPublisher; outbox publishers drain to Kafka; notification-webhook consumes payment.approved; Schema Registry with subject naming + compatibility rules. | F129: 1 | G129: lib-events, all outbox services | H129: Audit 2026-06-10 / WBS v3 re-baseline | I129: 10 | J129: 17.1 | K129: Events flow producer→Kafka→consumer in compose stack | L129: Backend | M129: 5 | R129: NOT STARTED | S129: R1
A130: 17.5 | B130: 17 | C130: 17. Real-Stack Gap Closure | D130: Stub→REST client flip, E2E verified | E130: Promote Rest*Client @Primary impls to verified: payment-executor's 7 clients and ops-partner-bff's 10 clients exercised against live services on the compose stack; delete/demote stubs to test scope. | F130: 2 | G130: payment-executor, ops-partner-bff | H130: Audit 2026-06-10 / WBS v3 re-baseline | I130: 10 | J130: 17.1,17.2 | K130: Inter-service REST calls verified E2E; stubs test-only | L130: Backend | M130: 3 | R130: NOT STARTED | S130: R2
A131: 17.6 | B131: 17 | C131: 17. Real-Stack Gap Closure | D131: Registry persistence (scheme/rule/treasury) | E131: Persist Scheme, Routing-Rule and Treasury registries in config-registry (currently in-memory/seed): entities, Flyway, CRUD endpoints, effective-dating. | F131: 1 | G131: config-registry | H131: Audit 2026-06-10 / WBS v3 re-baseline | I131: 8 | J131: 17.2 | K131: Registries survive restart; CRUD + ITs green | L131: Backend | M131: 3 | R131: NOT STARTED | S131: R1
A132: 17.7 | B132: 17 | C132: 17. Real-Stack Gap Closure | D132: MongoDB merchant/QR mirror | E132: Stand up MongoDB for merchant-qr-data (per architecture diagram); move lookup store from memory to Mongo; nightly sync job skeleton. | F132: 2 | G132: merchant-qr-data | H132: Audit 2026-06-10 / WBS v3 re-baseline | I132: 5 | J132: 17.1 | K132: Mongo-backed merchant lookup with ITs | L132: Backend | M132: 2 | R132: NOT STARTED | S132: R1
A133: 17.8 | B133: 17 | C133: 17. Real-Stack Gap Closure | D133: Object storage (MinIO) for files | E133: S3-compatible MinIO in compose; statements, recon files and ZP batch files stored/retrieved via a small lib-storage client. | F133: 2 | G133: settlement, scheme-adapter, BFF | H133: Audit 2026-06-10 / WBS v3 re-baseline | I133: 5 | J133: 17.1 | K133: Files round-trip through MinIO | L133: Backend | M133: 2 | R133: NOT STARTED | S133: R1
A134: 18.1 | B134: 18 | C134: 18. Missing Components | D134: ops-partner-bff legitimization & real wiring | E134: The BFF was built ahead of tickets (19 endpoints + 18 test classes). Legitimize in WBS; wire its 10 clients to real services; add auth pass-through. | F134: 2 | G134: ops-partner-bff | H134: Audit 2026-06-10 / WBS v3 re-baseline | I134: 6 | J134: 17.5 | K134: BFF serves both UIs from live services | L134: Backend | M134: 2 | R134: NOT STARTED | S134: R2
A135: 18.2 | B135: 18 | C135: 18. Missing Components | D135: Nginx WAF edge | E135: Nginx reverse proxy + WAF rules in front of api-gateway and the UIs per the architecture diagram (decision 18.7 governs final edge shape). | F135: 2 | G135: edge | H135: Audit 2026-06-10 / WBS v3 re-baseline | I135: 6 | J135: 18.7 | K135: Nginx fronts the compose stack with WAF ruleset | L135: DevOps | M135: 2 | R135: NOT STARTED | S135: R3
A136: 18.3 | B136: 18 | C136: 18. Missing Components | D136: SFTP Gateway service | E136: Dedicated SFTP gateway (per architecture diagram) brokering KFTC batch file exchange: inbound/outbound directories, PGP encrypt/decrypt, key mgmt, pickup/drop schedule. | F136: 2 | G136: sftp-gateway | H136: Audit 2026-06-10 / WBS v3 re-baseline | I136: 8 | J136: 17.8 | K136: ZP files flow disk↔SFTP↔adapter in compose stack | L136: Backend | M136: 3 | R136: NOT STARTED | S136: R2
A137: 18.4 | B137: 18 | C137: 18. Missing Components | D137: Real authentication (replace demo login) | E137: Replace password=demo stub: auth-identity issues JWTs (OAuth2 password/client-credentials), BFF validates, RBAC roles enforced, refresh rotation, login rate-limit. | F137: 2 | G137: auth-identity, ops-partner-bff, UIs | H137: Audit 2026-06-10 / WBS v3 re-baseline | I137: 10 | J137: 17.2 | K137: Login works end-to-end with real JWT + RBAC | L137: Backend | M137: 4 | R137: NOT STARTED | S137: R3
... A145: 20.5 | B145: 20 | C145: 20. Phase-2+ Scheme Adapters | D145: PromptPay adapter (Thailand) | E145: PromptPay scheme adapter. Expand WBS when partner contract lands. | F145: 4 | G145: scheme-adapter-promptpay | H145: Audit 2026-06-10 / WBS v3 re-baseline | I145: 35 | J145: 9.1,16.2 | K145: PromptPay adapter certified | L145: Backend | M145: 1 | R145: NOT STARTED | S145: R8
A146: 21.0 | B146: 21 | C146: 21. Partner Setup re-baseline | D146: WS 21 — Partner Setup re-baseline (8 vertical slices) | E146: Re-baselines Partner Setup against DAT-03 §4.3 + PRD-07 §5.3: the 4-field demo (/partners/new with partnerId/type/settlementCurrency/settlementRoundingMode) is replaced by an 8-step wizard delivered as 8 vertical slices (21.1–21.8). Architecture locked by ADR-006..014. Sole source of truth: docs/PARTNER_SETUP_PLAN.md. | F146: 2 | G146: Cross-cutting (config-registry + ops-partner-bff + admin-ui + auth-identity + prefunding + notification-webhook + kyb-adapter) | H146: PARTNER_SETUP_PLAN.md; DAT-03 §4.3; PRD-07 §5.3; ADR-006..014 | I146: 60 | J146: 10.3 (superseded), 8.x, 13.x | K146: 8-step partner onboarding wizard, end-to-end FSM, full audit + 4-eyes + KYB + bitemporal aggregate | L146: FS | M146: 179 | N146: 0 | O146: 0 | P146: 179 | Q146: 0% | R146: NOT STARTED (re-baselined 2026-06-11) | S146: R0..R3
A147: 21.1 | B147: 21 | C147: 21. Partner Setup re-baseline | D147: Slice 1 — Identity + Foundation | E147: Wizard scaffold + step 1 (Identity). Foundation primitives every later slice depends on: resolve String↔Long Partner ID schism (adopt partner_id BIGINT surrogate + partner_code VARCHAR(20) unique business key per ADR-013 Expand/Backfill/Contract); collapse 5 Partner DTO shapes into canonical PartnerView (read) + PartnerCommand (write) in lib-api-contracts. Bitemporal partner table (ADR-010 SCD-Type-6, valid_from/to + recorded_at/superseded_at + current-flag). change_request table + Spring State Machine (ADR-008 DRAFT→PROPOSED→APPROVED→APPLIED, REJECTED terminal). audit_log infra (ADR-007 dedicated audit Postgres DB, INSERT-only role, hash chain, Kafka topic gmepay.audit.partner, lib-audit). Keycloak service (ADR-011 docker-compose Rocky 9, Postgres-backed); api-gateway becomes OAuth2 resource server; ops-partner-bff password=demo retired. Identity fields on partner: partner_code UNIQUE, legal_name_local, legal_name_romanized, tax_id + type discriminator (KR-BRN/KH-VAT/VN-MST/SG-UEN/generic), country_of_incorporation ISO-3166-α2, legal_form enum (CORP/LLC/MTO/EMI/BANK/OTHER), structured registered_address + operating_address, lei ISO-17442. Draft endpoints POST/PATCH/GET /v1/admin/partners/draft. RestConfigRegistryClient + admin-ui client.js updated. UI: wizard scaffold (8 tabs/stepper, server-side draft persistence per ADR-012), step-1 form with Yup regional validators, draft list with Resume button, Keycloak OIDC login replaces demo auth. | F147: 1 | G147: Cross-cutting / Foundation | H147: PARTNER_SETUP_PLAN.md §Slice 1; ADR-007/008/010/011/012/013 | I147: 10 | J147: 10.1, 8.2, 13.1, 13.2 | K147: Bitemporal partner aggregate + change_request FSM + audit_log + Keycloak; wizard step 1 live | L147: FS | M147: 22 | N147: 0 | O147: 0 | P147: 22 | Q147: 0% | R147: NOT STARTED | S147: R0
A148: 21.2 | B148: 21 | C148: 21. Partner Setup re-baseline | D148: Slice 2 — Contacts | E148: Wizard step 2 + 4-eyes machinery surfaced in UI. Backend: partner_contact child table (bitemporal) — id BIGSERIAL, partner_id FK, role enum (OPS_24X7/FINANCE/COMPLIANCE_MLRO/TECH/LEGAL/INCIDENT), name, email, phone_e164, is_authorized_signatory BOOL, notes. Reuse change_request from Slice 1. BFF: PATCH /v1/admin/partners/draft/{id}/step-2 (bulk replace), POST /v1/admin/partners/{id}/contacts (propose change), POST /v1/admin/partners/change-requests/{id}/approve. UI: multi-row contact editor with role dropdown + E.164 phone validation; generic Approval queue page (checker sees PROPOSED CRs, Approve/Reject with reason); read-only paginated audit log viewer on partner detail page. | F148: 2 | G148: Admin + BFF + config-registry | H148: PARTNER_SETUP_PLAN.md §Slice 2; ADR-008 | I148: 8 | J148: 21.1 | K148: partner_contact entity + approval queue UI + audit log viewer | L148: FS | M148: 15 | N148: 0 | O148: 0 | P148: 15 | Q148: 0% | R148: NOT STARTED | S148: R1
A149: 21.3 | B149: 21 | C149: 21. Partner Setup re-baseline | D149: Slice 3 — KYB | E149: Wizard step 3 + document vault + KYB screening adapter. Backend: MinIO bucket gmepay-partner-vault with object-lock compliance mode (ADR-006); lib-vault wraps MinIO SDK with virus-scan hook + Vault-key encryption. partner_document (bitemporal): id, partner_id FK, doc_type enum (LICENSE/CERT_INCORPORATION/AOA/BOARD_RESOLUTION/UBO_DECLARATION/FINANCIALS/CBDDQ/OTHER), vault_uri, version, expiry_date, verified_by, verified_at. partner_kyb (bitemporal): risk_rating (LOW/MEDIUM/HIGH), risk_rationale, next_review_date, license_type/number/authority/expiry, ubo_set_jsonb (array of {name, ownership_pct, is_pep, country}), wolfsberg_cbddq_doc_id FK. KybProvider port in lib-kyb (ADR-009). StubKybAdapter for internal dev; OctaKybAdapter lands when sandbox creds arrive. Kafka topic gmepay.kyb.screening, outbox-published same txn. New service services/kyb-adapter (Spring Boot module). UI: license details, UBO entry table (name + ownership% + PEP toggle + country), drag-drop document upload, Wolfsberg CBDDQ upload, Run screening button, document viewer modal with version history, screening result panel (latest result, decision history, rescreen). | F149: 2 | G149: KYB + Vault + Admin | H149: PARTNER_SETUP_PLAN.md §Slice 3; ADR-006 (Vault), ADR-009 (KYB port) | I149: 10 | J149: 21.1 | K149: MinIO vault + lib-vault + kyb-adapter service + partner_document/partner_kyb tables + step-3 UI | L149: FS | M149: 18 | N149: 0 | O149: 0 | P149: 18 | Q149: 0% | R149: NOT STARTED | S149: R1
A150: 21.4 | B150: 21 | C150: 21. Partner Setup re-baseline | D150: Slice 4 — Banking & Settlement | E150: Wizard step 4 — settlement bank accounts, settlement cycle, methods, calendars. Backend: partner_bank_account (bitemporal) — id, partner_id FK, currency ISO-4217, bank_name, bic_swift, iban_or_account_number, account_holder_name, bank_country ISO-3166, intermediary_bic (opt), verification_status (UNVERIFIED/KFTC_VERIFIED/BANK_LETTER/MICRO_DEPOSIT), verification_evidence_doc_id FK, verification_date, is_primary BOOL, swift_charge_bearer (OUR/BEN/SHA), purpose (PAYOUT/FLOAT_TOPUP/REFUND). partner_settlement_config (bitemporal): partner_id PK, cycle_t_plus_n INT, cutoff_time, cutoff_timezone, settlement_method (SWIFT_MT103/KR_FIRM_BANKING/BAKONG/NAPAS_247/PROMPT_PAY/FAST_SG/OTHER). business_day_calendar seeded with Korean + ASEAN holidays go-live + 2 years (Chuseok, Tet, Songkran, Lunar New Year, etc.). KFTC 계좌실명조회 verification stub — port abstraction AccountVerificationProvider with KftcVerificationAdapter + StubVerificationAdapter. UI: bank account multi-row editor with per-row verification button, settlement config panel (cycle/cutoff/method/timezone picker), settlement preview ("with these settings, your Mon 11:30 KST txn pays out Wed 11:30 KST"). | F150: 2 | G150: Banking + Settlement | H150: PARTNER_SETUP_PLAN.md §Slice 4; ADR-008; CAL-01 holiday calendars | I150: 9 | J150: 21.2 | K150: partner_bank_account + partner_settlement_config + business_day_calendar + KFTC verification port + step-4 UI | L150: FS | M150: 20 | N150: 0 | O150: 0 | P150: 20 | Q150: 0% | R150: NOT STARTED | S150: R2
A151: 21.5 | B151: 21 | C151: 21. Partner Setup re-baseline | D151: Slice 5 — Prefunding (OVERSEAS only) | E151: Wizard step 5 + wire-up of existing PartnerBalanceEntity into partner-create txn. Backend: when partner is activated with funding_model=PREFUNDED or HYBRID, prefunding service creates balance row in same change_request. partner_prefunding_config (bitemporal): funding_model (PREFUNDED/POSTPAID/HYBRID), opening_balance_usd, low_balance_threshold_usd (default 10000), alert_tier_70/85/95_pct, credit_limit_usd (NULL=no limit), auto_suspend_on_breach BOOL, float_top_up_bank_account_id FK (purpose=FLOAT_TOPUP), top_up_reference_pattern VARCHAR (e.g. GMP-{partner_code}-{yyyyMMdd}), collateral_amount_usd (opt). Tier-alert generation: Kafka topic gmepay.prefunding.alert produced when balance crosses threshold; notification-webhook consumes. Auto-suspend: balance<0 (or breach + auto_suspend_on_breach=true) publishes change_request(aggregate=partner, payload=status:SUSPENDED) with proposed_by=system — requires operator approval to lift. UI step 5 (OVERSEAS only): funding model radio, opening balance + ccy, threshold inputs with live preview, credit limit, top-up bank picker (filtered to FLOAT_TOPUP purpose), reference pattern preview. Prefunding dashboard tile on partner detail page: current balance, threshold gauge with tier coloring, recent top-ups, recent alerts. | F151: 2 | G151: Prefunding + Admin | H151: PARTNER_SETUP_PLAN.md §Slice 5 | I151: 8 | J151: 21.4 | K151: partner_prefunding_config + PartnerBalanceEntity wired into create txn + tier alerts + auto-suspend + step-5 UI | L151: FS | M151: 17 | N151: 0 | O151: 0 | P151: 17 | Q151: 0% | R151: NOT STARTED | S151: R2
A152: 21.6 | B152: 21 | C152: 21. Partner Setup re-baseline | D152: Slice 6 — Commercial Terms | E152: Wizard step 6 — financial-correctness slice (ccy split + rules + fees + FX + limits + contract). Backend: split settlement_currency into collection_ccy + settle_a_ccy (DAT-03 §4.3 + PRD-07 §5.3.2) via Expand/Backfill/Contract (ADR-013) across 3 releases. Rule persistence: today only POST /v1/rules/validate exists; add POST /v1/rules (create) + GET /v1/rules (list per partner) + PUT /v1/rules/{id} (update via change_request). Schema includes existing lib-domain Rule.validate "m_a + m_b ≥ 2%" invariant. partner_fee_schedule (bitemporal) per (partner × scheme × direction): fixed_fee, bps_fee, tier table (volume bands → bps). partner_fx_config (bitemporal): margin_bps, reference_rate_source (SEOUL_FX_BROKER/PARTNER_PROVIDED/MID_MARKET), quote_hold_seconds (default 300, range 60–1800). partner_limits (bitemporal): per_txn_min/max_usd, daily/monthly/annual_cap_usd. 소액해외송금업 hard-enforced server-side: per_txn ≤ 5000 USD, annual ≤ 50000 USD for that license type. partner_contract (bitemporal): effective_from/to, auto_renewal BOOL, notice_period_days, refund_chargeback_policy (PARTNER_BEARS/MERCHANT_BEARS/SHARED), termination_reason. transaction-mgmt + rate-fx updated to read new collection_ccy / settle_a_ccy split. UI step 6: split ccy picker, rule editor (multi-row per scheme/direction with margin sliders), fee schedule, FX margin slider + reference source + quote hold, limits with 소액해외송금업 visual cap markers, contract dates + auto-renewal toggle. | F152: 2 | G152: Pricing + FX + Limits + Contract | H152: PARTNER_SETUP_PLAN.md §Slice 6; ADR-013 Expand/Backfill/Contract; DAT-03 §4.3; PRD-07 §5.3.2 | I152: 12 | J152: 21.4 | K152: collection_ccy/settle_a_ccy split + rule persistence + fee schedule + FX config + limits + contract + step-6 UI | L152: FS | M152: 25 | N152: 0 | O152: 0 | P152: 25 | Q152: 0% | R152: NOT STARTED | S152: R2
A153: 21.7 | B153: 21 | C153: 21. Partner Setup re-baseline | D153: Slice 7 — Schemes & Corridors | E153: Wizard step 7 — scheme enablement + corridor matrix + per-partner scheme credentials. Backend: partner_scheme (bitemporal): partner_id, scheme_id, direction (INBOUND/OUTBOUND/BOTH), role (ACQUIRER/ISSUER/BOTH), zeropay_merchant_id, zeropay_sub_merchant_id, kftc_institution_code, partner_type_char (D/I — Zp0011 derivation). partner_corridor (bitemporal): partner_id, src_country, src_ccy, dst_country, dst_ccy, go_live_date, is_active. SchemeRouter rewrite from hardcoded KR→ZEROPAY to data-driven (reads partner_scheme join). Per-partner scheme credentials stored in Vault (ADR-006 pattern), referenced by partner_scheme.vault_secret_id. Approval method per (partner × scheme × payment_mode CPM/MPM): approval_method enum (CONFIRMATION/SILENT) — closes OI-01 / 1.2-T03. Operating hours per scheme (settlement cutoffs): seeded for ZeroPay (24×7 with KFTC 16:30 KST cutoff), Bakong (24×7 with NBC 09:00–15:00 ICT), etc. UI step 7: scheme enablement matrix (rows=schemes, columns=direction × role, checkboxes), per-row drill-down for ZeroPay specifics (merchantId, sub-merchantId, institution code, D/I, approval method per CPM/MPM), corridor matrix builder, operating hours preview. | F153: 2 | G153: Schemes + Corridors + Routing | H153: PARTNER_SETUP_PLAN.md §Slice 7; ADR-006; OI-01 | I153: 10 | J153: 21.6 | K153: partner_scheme + partner_corridor + data-driven SchemeRouter + Vault-stored creds + step-7 UI | L153: FS | M153: 22 | N153: 0 | O153: 0 | P153: 22 | Q153: 0% | R153: NOT STARTED | S153: R2
A154: 21.8 | B154: 21 | C154: 21. Partner Setup re-baseline | D154: Slice 8 — Credentials + Lifecycle + Reporting | E154: Wizard step 8 — credential issuance + full FSM + regulatory reporting attributes. Backend: wire existing auth-identity/ApiKeyEntity + PrincipalEntity + notification-webhook/WebhookEndpointEntity into partner-create txn (the wire-up debt). Generate API key + HMAC secret on activation, return plaintext ONCE in response, store hash. IP allowlist: partner_ip_allowlist (up to 10 CIDRs); api-gateway pre-signature 403 enforcement. mTLS cert exchange: partner_mtls_cert (bitemporal) — cert_pem, fingerprint_sha256, expiry_date, status; mTLS verification at Nginx layer (ADR-002). Sandbox vs production credential pairs: partner_credential_environment enum (SANDBOX/PRODUCTION); sandbox prefix pk_test_/sk_test_. Credential rotation: scheduled job proposes rotation change_request at 11 months (12-month rotation per SEC-09); revoke endpoint with audit_log entry. Full FSM: Draft → KYB-Pending → KYB-Approved → Contract-Signed → Sandbox → UAT → Live → Suspended → Terminated. Transitions are change_request-gated; go-live + suspend require 4-eyes. Activation pre-condition gate: returns 422 + unmet[] until legal_name set, KYB approved, ≥1 verified bank account per settle_ccy, contracts signed, prefunding row created if OVERSEAS, ≥4 role contacts, ≥1 scheme enabled, sanctions clear or operator-overridden. Post-activation immutability: partner_code, country_of_incorporation, partner_type, collection_ccy, settle_a_ccy locked after first Live transition; mutations → 400 IMMUTABLE_AFTER_ACTIVATION. Suspension reason codes: LIMIT_BREACH/SANCTIONS_HIT/CREDENTIAL_COMPROMISE/KYB_LAPSED/CONTRACT_EXPIRED/OPERATOR_INITIATED. BOK 외환거래보고 attributes: bok_txn_code, bok_fx_reporting_category (INDIVIDUAL_AGGREGATE/INSTITUTIONAL), bok_remitter_type. Hometax e-tax-invoice: hometax_issuer_cert_id FK to vault doc, vat_treatment (ZERO_RATED_EXPORT/STANDARD/EXEMPT). KoFIU STR/CTR: kofiu_entity_id, ctr_threshold_krw (default 10,000,000), per-corridor STR enable flag. PIPA cross-border PII transfer notice: pipa_jurisdiction_allowlist[], legal_basis_code enum. Travel Rule (TRP/Sygna/IVMS101): travel_rule_protocol enum + endpoint config; ≥KRW 1M transfers must include IVMS101 originator + beneficiary block. UI step 8: Review tab (full summary with anchor jumps), Activate button (calls pre-condition gate, shows unmet[]), one-time credential modal (API key + HMAC + webhook signing secret, copy-to-clipboard, dismiss confirmation), confirmation operator stored secrets. Partner detail page (post-activation): status header with FSM menu, credential rotation panel, audit log full view, BOK/Hometax/KoFIU reporting settings tab, status-action menu (Suspend/Reactivate/Terminate with reason). | F154: 3 | G154: Credentials + FSM + Regulatory Reporting | H154: PARTNER_SETUP_PLAN.md §Slice 8; ADR-002 (mTLS); ADR-008 (4-eyes); SEC-09 rotation | I154: 13 | J154: 21.5, 21.7 | K154: Credential issuance + full lifecycle FSM + activation gate + BOK/Hometax/KoFIU/PIPA/Travel-Rule reporting attrs + step-8 UI | L154: FS | M154: 40 | N154: 0 | O154: 0 | P154: 40 | Q154: 0% | R154: NOT STARTED | S154: R3

Sheet Completion Plan v3
A1: GMEPay+ — Completion Plan v3 (re-baselined after the 2026-06-10 code audit)
A2: Every WBS code is mapped to one executable completion phase R0–R8. Sequence is dependency-true: R0 unlocks Testcontainers/compose; R1 makes persistence real; R2 proves the money path E2E; R3–R6 are productionization; R7 is external-party bound; R8 is launch.
A4: Phase | B4: Name | C4: Owner | D4: WBS codes | E4: Tickets | F4: Done | G4: Partial | H4: Not started | I4: % D+P | J4: Exit gate | K4: External blockers
A5: R0 | B5: Decisions & build environment | C5: AI agents + GME + user | D5: 1.1 1.2 1.3 1.4 2.1 2.2 2.3 17.1 18.7 | E5: 190 | F5: 6 | G5: 40 | H5: 144 | I5: 24% | J5: Docker-capable CI green; stack ADRs signed (Kafka/RabbitMQ, Gateway/Nginx, Mongo) | K5: —
A6: R1 | B6: Persistence & real wiring (gap closure) | C6: AI agents | D6: 2.4 2.5 3.1 3.2 3.3 3.4 3.5 3.6 3.7 4.1 4.6 4.7 6.1 6.2 6.3 6.4 17.2 17.3 17.4 17.6 17.7 17.8 | E6: 424 | F6: 3 | G6: 81 | H6: 340 | I6: 20% | J6: All 12 services on real PostgreSQL; Redis/Kafka/Mongo/MinIO wired; registries persistent | K6: —
A7: R2 | B7: Money-path E2E on compose stack | C7: AI agents | D7: 4.2 4.3 4.4 4.5 4.8 4.9 5.1 5.2 5.3 5.4 5.5 5.6 5.7 5.8 6.5 7.1 7.2 7.3 7.4 7.6 8.3 8.4 8.5 8.6 8.7 9.1 9.4 9.9 15.3 15.4 17.5 18.1 18.3 18.6 | E7: 715 | F7: 20 | G7: 131 | H7: 564 | I7: 21% | J7: Scripted E2E quote→commit→settlement+rounding residual→webhook green in CI | K7: —
A8: R3 | B8: Edge & security | C8: AI agents + GME Security | D8: 8.1 8.2 8.8 13.1 13.2 13.3 13.4 13.5 13.6 13.9 18.2 18.4 | E8: 272 | F8: 8 | G8: 24 | H8: 240 | I8: 12% | J8: Nginx WAF up; real JWT auth + RBAC; Vault for secrets; HMAC/idempotency at edge | K8: —
A9: R4 | B9: UI completion against live BFF | C9: AI agents | D9: 2.6 10.1 10.2 10.3 10.4 10.5 10.6 10.7 10.8 10.9 10.10 10.11 11.1 11.2 11.3 11.4 11.5 11.6 11.7 12.1 12.2 12.3 12.4 12.5 18.5 | E9: 717 | F9: 0 | G9: 80 | H9: 637 | I9: 11% | J9: All admin + portal WBS screens functional vs live BFF; contract-drift CI gate | K9: —
A10: R5 | B10: Infrastructure & observability | C10: GME DevOps (agents author IaC) | D10: 14.1 14.2 14.3 14.4 14.5 14.6 14.7 14.8 16.1 | E10: 268 | F10: 0 | G10: 0 | H10: 268 | I10: 0% | J10: Staging on K8s via CI/CD; OTel+Prometheus/Grafana+ELK+Jaeger; backup/DR drill | K10: —
A11: R6 | B11: Hardening, performance, pen test | C11: Agents author; GME validates | D11: 13.10 15.1 15.2 15.5 15.7 15.8 15.10 | E11: 256 | F11: 1 | G11: 14 | H11: 241 | I11: 6% | J11: NFR-10 load targets met; pen test passed; regression suite green | K11: —
A12: R7 | B12: Compliance & certification | C12: GME + external parties | D12: 7.5 8.9 8.10 9.2 9.3 9.5 9.6 9.7 9.8 9.10 13.7 13.8 15.6 | E12: 392 | F12: 3 | G12: 41 | H12: 348 | I12: 11% | J12: KFTC/ZeroPay certified; BOK FX1014/1015 verified; Hometax integrated; AML live | K12: KFTC test env, BOK OI-03, Hometax OI-02
A13: R8 | B13: UAT, go-live & hypercare | C13: GME business + partners | D13: 1.5 1.6 15.9 16.2 16.3 16.4 16.5 16.6 20.1 20.2 20.3 20.4 20.5 | E13: 253 | F13: 0 | G13: 1 | H13: 252 | I13: 0% | J13: UAT signed; production cutover rehearsed; 14-day hypercare; Phase-2 adapters start | K13: —
B14: TOTAL | E14: 3487 | F14: 41 | G14: 412 | H14: 3034 | I14: 13%

Sheet Summary
A1: GMEPay+ — WBS Summary & Effort Rollup
A2: Indicative planning estimates (person-days). See Legend for assumptions.
A4: Effort by Workstream
A5: WS # | B5: Workstream | C5: Tasks | D5: Effort (PD) | E5: % of Total
A6: 1 | B6: 1. Project Management & Mobilization | C6: =COUNTIF(WBS!$B$2:$B$125,A6) | D6: =SUMIF(WBS!$B$2:$B$125,A6,WBS!$I$2:$I$125) | E6: =D6/$D$22
A7: 2 | B7: 2. Architecture & Technical Foundation | C7: =COUNTIF(WBS!$B$2:$B$125,A7) | D7: =SUMIF(WBS!$B$2:$B$125,A7,WBS!$I$2:$I$125) | E7: =D7/$D$22
A8: 3 | B8: 3. Data Layer & Persistence | C8: =COUNTIF(WBS!$B$2:$B$125,A8) | D8: =SUMIF(WBS!$B$2:$B$125,A8,WBS!$I$2:$I$125) | E8: =D8/$D$22
A9: 4 | B9: 4. Rate Engine & FX | C9: =COUNTIF(WBS!$B$2:$B$125,A9) | D9: =SUMIF(WBS!$B$2:$B$125,A9,WBS!$I$2:$I$125) | E9: =D9/$D$22
A10: 5 | B10: 5. Transaction Processing (MPM/CPM) | C10: =COUNTIF(WBS!$B$2:$B$125,A10) | D10: =SUMIF(WBS!$B$2:$B$125,A10,WBS!$I$2:$I$125) | E10: =D10/$D$22
A11: 6 | B11: 6. Prefunding & Wallet Ledger | C11: =COUNTIF(WBS!$B$2:$B$125,A11) | D11: =SUMIF(WBS!$B$2:$B$125,A11,WBS!$I$2:$I$125) | E11: =D11/$D$22
A12: 7 | B12: 7. Settlement, Reconciliation & Revenue | C12: =COUNTIF(WBS!$B$2:$B$125,A12) | D12: =SUMIF(WBS!$B$2:$B$125,A12,WBS!$I$2:$I$125) | E12: =D12/$D$22
A13: 8 | B13: 8. Partner (Northbound) API | C13: =COUNTIF(WBS!$B$2:$B$125,A13) | D13: =SUMIF(WBS!$B$2:$B$125,A13,WBS!$I$2:$I$125) | E13: =D13/$D$22
A14: 9 | B14: 9. QR Scheme Integration (ZeroPay) | C14: =COUNTIF(WBS!$B$2:$B$125,A14) | D14: =SUMIF(WBS!$B$2:$B$125,A14,WBS!$I$2:$I$125) | E14: =D14/$D$22
A15: 10 | B15: 10. Admin System | C15: =COUNTIF(WBS!$B$2:$B$125,A15) | D15: =SUMIF(WBS!$B$2:$B$125,A15,WBS!$I$2:$I$125) | E15: =D15/$D$22
A16: 11 | B16: 11. Partner Portal | C16: =COUNTIF(WBS!$B$2:$B$125,A16) | D16: =SUMIF(WBS!$B$2:$B$125,A16,WBS!$I$2:$I$125) | E16: =D16/$D$22
A17: 12 | B17: 12. UX/UI & Frontend Foundation | C17: =COUNTIF(WBS!$B$2:$B$125,A17) | D17: =SUMIF(WBS!$B$2:$B$125,A17,WBS!$I$2:$I$125) | E17: =D17/$D$22
... A21: 16 | B21: 16. Deployment, Go-Live & Hypercare | C21: =COUNTIF(WBS!$B$2:$B$125,A21) | D21: =SUMIF(WBS!$B$2:$B$125,A21,WBS!$I$2:$I$125) | E21: =D21/$D$22
B22: TOTAL | C22: =SUM(C6:C21) | D22: =SUM(D6:D21) | E22: =D22/D22
A25: Effort by Phase
A26: Phase | B26: Description | C26: Tasks | D26: Effort (PD) | E26: % of Total
A27: 1 | B27: P1 — Build Core (Apr 10–Jun 20) | C27: =COUNTIF(WBS!$F$2:$F$125,A27) | D27: =SUMIF(WBS!$F$2:$F$125,A27,WBS!$I$2:$I$125) | E27: =D27/$D$31
A28: 2 | B28: P2 — Integrate ZeroPay (May 15–Jul 31) | C28: =COUNTIF(WBS!$F$2:$F$125,A28) | D28: =SUMIF(WBS!$F$2:$F$125,A28,WBS!$I$2:$I$125) | E28: =D28/$D$31
A29: 3 | B29: P3 — Launch Domestic (Aug 1–Oct 10) | C29: =COUNTIF(WBS!$F$2:$F$125,A29) | D29: =SUMIF(WBS!$F$2:$F$125,A29,WBS!$I$2:$I$125) | E29: =D29/$D$31
A30: 4 | B30: P4 — Launch Overseas (Oct 1–Dec 10) | C30: =COUNTIF(WBS!$F$2:$F$125,A30) | D30: =SUMIF(WBS!$F$2:$F$125,A30,WBS!$I$2:$I$125) | E30: =D30/$D$31
B31: TOTAL | C31: =SUM(C27:C30) | D31: =SUM(D27:D30) | E31: =D31/D31
A34: Indicative Conversions
A35: Total effort (person-days) | B35: =D22
A36: Person-weeks (5 PD/week) | B36: =D22/5
A37: Person-months (21 PD/month) | B37: =D22/21
A38: Calendar months @ 6 FTE | B38: =D22/21/6
A39: Calendar months @ 8 FTE | B39: =D22/21/8

Sheet Phases & Milestones
A1: GMEPay+ — Phases & Key Milestones
A2: Go-live: October 10, 2026 (GME Remit domestic). Critical path: 한결원/KFTC test environment available by mid-May 2026.
A4: Phase | B4: Name | C4: Period (2026) | D4: Duration | E4: Gate / Entry Criteria | F4: Primary Deliverables
A5: P1 | B5: Build Core | C5: Apr 10 – Jun 20 | D5: ~10 weeks | E5: Design sign-off | F5: Hub Core, Rate Engine, Data layer, Partner API, Admin foundation
A6: P2 | B6: Integrate ZeroPay | C6: May 15 – Jul 31 | D6: ~11 weeks (overlap) | E6: KFTC test env ready | F6: Scheme adapter, ZP00xx batch flows, Settlement & reconciliation
A7: P3 | B7: Launch Domestic | C7: Aug 1 – Oct 10 | D7: ~10 weeks | E7: UAT sign-off | F7: GME Remit live, Partner Portal, Perf & security testing, Go-live
A8: P4 | B8: Launch Overseas | C8: Oct 1 – Dec 10 | D8: ~10 weeks | E8: P3 stable | F8: T-Bank/SendMN onboarding, prefunding live, hypercare, handover
A11: Key Milestones
A12: Milestone | B12: Target | C12: Depends on
A13: Architecture & design sign-off | B13: Apr 2026 | C13: Requirements walkthrough
A14: Rate engine passes all test vectors | B14: May 2026 | C14: WS4, WS15.3
A15: KFTC/한결원 test environment available | B15: Mid-May 2026 | C15: External (KFTC)
A16: Partner API sandbox live | B16: May 2026 | C16: WS8
A17: ZeroPay batch round-trip certified | B17: Jul 2026 | C17: WS9.10
A18: Settlement & reconciliation verified | B18: Jul 2026 | C18: WS7, WS9.6
A19: UAT sign-off | B19: Sep 2026 | C19: WS15.9
A20: GME Remit domestic GO-LIVE | B20: Oct 10, 2026 | C20: WS16.2
A21: First overseas partner live | B21: Within 3 months of go-live | C21: WS16.3

Sheet Legend
A1: GMEPay+ — WBS Legend, Conventions & Assumptions
A3: Column definitions
A4: WBS Code | B4: Hierarchical identifier (workstream.task).
A5: Phase | B5: Primary delivery phase (1–4). Some tasks span phases; primary phase shown for rollup.
A6: Component | B6: Hub Core / Admin / Portal / API-N (northbound) / API-S (scheme) / Infra / Cross-cutting.
A7: Source Doc(s) | B7: Specification document(s) the task derives from (codes per DOC-00).
A8: Effort (PD) | B8: Indicative effort in person-days for estimation; refine with vendor.
A9: Dependencies | B9: Predecessor WBS codes that should complete (or substantially progress) first.
A10: Primary Role | B10: Lead discipline; most tasks need supporting roles too.
A12: Role abbreviations
A13: PM / BA | B13: Project Manager / Business Analyst
A14: ARCH | B14: Solution/Software Architect
A15: BE / FE / FS | B15: Backend / Frontend / Full-stack Engineer
A16: DBA | B16: Database Engineer
A17: UX | B17: UX/UI Designer
A18: DevOps | B18: DevOps / SRE
A19: QA | B19: Quality Assurance / Test Engineer
A20: Sec | B20: Security Engineer
A22: Source document codes
A23: BRD-01 / SAD-02 / DAT-03 | B23: Business Requirements / System Architecture / Data Model
A24: RATE-04 / API-05 / SCH-06 | B24: Rate Engine / Partner API / ZeroPay Integration
A25: PRD-07 / PRD-08 / SEC-09 | B25: Admin System / Partner Portal / Security & Compliance
A26: NFR-10 / UX-11 / QA-12 | B26: NFR & SLA / UX-UI / Test Plan
A27: OPS-13 / PM-14 / REF-15 | B27: DevOps & Runbook / Project Plan / Glossary
A28: DOC-00 | B28: Documentation Index & Handover
A30: Estimating assumptions
A31: Basis | B31: Effort is indicative for planning only, derived from the specification scope; not a fixed-price commitment.
A32: Working calendar | B32: 5 person-days/week; 21 person-days/month assumed.
A33: Exclusions | B33: Partner app development, merchant onboarding, and KFTC-side build are out of scope (GME/partner/scheme responsibilities).
A34: Open items | B34: OI-01 customer-approval UX, OI-02 tax-invoice API, OI-03 BOK reporting format may change scope when resolved (see WS1.2).
A35: Risk buffer | B35: Add project contingency (e.g. 15–20%) on top of the WBS total; not included here.
